<annotation>
	<folder></folder>
	<filename>IMG_0843.jpeg.rf.c2b7ef007229a6e9b7ff887602b0c550.jpg</filename>
	<path>IMG_0843.jpeg.rf.c2b7ef007229a6e9b7ff887602b0c550.jpg</path>
	<source>
		<database>roboflow.ai</database>
	</source>
	<size>
		<width>3024</width>
		<height>4032</height>
		<depth>3</depth>
	</size>
	<segmented>0</segmented>
	<object>
		<name>3</name>
		<pose>Unspecified</pose>
		<truncated>0</truncated>
		<difficult>0</difficult>
		<occluded>0</occluded>
		<bndbox>
			<xmin>2502</xmin>
			<xmax>2573</xmax>
			<ymin>2221</ymin>
			<ymax>2283</ymax>
		</bndbox>
	</object>
	<object>
		<name>3</name>
		<pose>Unspecified</pose>
		<truncated>0</truncated>
		<difficult>0</difficult>
		<occluded>0</occluded>
		<bndbox>
			<xmin>1743</xmin>
			<xmax>1819</xmax>
			<ymin>1652</ymin>
			<ymax>1709</ymax>
		</bndbox>
	</object>
</annotation>
